[
    {
        "id": "112828461693258_426575550321541",
        "created_time": "2024-05-04T15:21:29+0000",
        "full_picture": "https://scontent-sjc3-1.xx.fbcdn.net/v/t39.30808-6/440180872_426575110321585_3204426970601118142_n.jpg?stp=dst-jpg_p720x720\u0026_nc_cat=111\u0026ccb=1-7\u0026_nc_sid=5f2048\u0026_nc_ohc=l6hH1GU5sToQ7kNvgGTqQxW\u0026_nc_ht=scontent-sjc3-1.xx\u0026edm=AJdBtusEAAAA\u0026oh=00_AfAOpXHl6PUCBq98ICRV5anOGBLs-R0wcIE8OkdcnuVHEQ\u0026oe=663F5213",
        "is_popular": false,
        "is_published": true,
        "is_hidden": false,
        "is_expired": false,
        "message": "▸ FINAL DEL PARTIDO ⏰\n\n📌 #FBCPiérola 4 - 1 #ChacaritaJr\n🏆 Liga del Cercado I Fecha 9\n\nGran Triunfo Azulgranas ❤💙💪🏼\n\n#ligadearequipa #fbcpierola #azulgrana #ardillasdelpierola",
        "permalink_url": "https://www.facebook.com/337153289263768/posts/426575550321541",
        "from": {
            "name": "FBC Piérola",
            "id": "112828461693258"
        }
    },
    {
        "id": "112828461693258_426513370327759",
        "created_time": "2024-05-04T13:30:08+0000",
        "full_picture": "https://scontent-sjc3-1.xx.fbcdn.net/v/t39.30808-6/440584246_426185173693912_4946571855655392148_n.jpg?stp=dst-jpg_p720x720\u0026_nc_cat=109\u0026ccb=1-7\u0026_nc_sid=5f2048\u0026_nc_ohc=tlGkO75ag-IQ7kNvgGIk-0s\u0026_nc_ht=scontent-sjc3-1.xx\u0026edm=AJdBtusEAAAA\u0026oh=00_AfCVgQZauqZYlrnfo8YkvqXS5l7iLV9WU5lkG4HTd7O6nw\u0026oe=663F404C",
        "is_popular": false,
        "is_published": true,
        "is_hidden": false,
        "is_expired": false,
        "message": "📣 ¡ARRANCAMOS EL PARTIDO!\n¡🐿 VAMOS AZULGRANAS! ❤💙\n\n#ligadearequipa #fbcpierola #azulgrana #ardillasdelpierola",
        "permalink_url": "https://www.facebook.com/337153289263768/posts/426513370327759",
        "from": {
            "name": "FBC Piérola",
            "id": "112828461693258"
        }
    },
    {
        "id": "112828461693258_426265353685894",
        "created_time": "2024-05-04T05:01:03+0000",
        "full_picture": "https://scontent-sjc3-1.xx.fbcdn.net/v/t39.30808-6/440577181_426184057027357_6757999464944078620_n.jpg?stp=dst-jpg_p720x720\u0026_nc_cat=103\u0026ccb=1-7\u0026_nc_sid=5f2048\u0026_nc_ohc=159Ouo95muoQ7kNvgFRI0TS\u0026_nc_ht=scontent-sjc3-1.xx\u0026edm=AJdBtusEAAAA\u0026oh=00_AfDFK6dgXUqX4xhXjzz6DXeblbGzZuPC6PoFOIof5sml8Q\u0026oe=663F3DEF",
        "is_popular": false,
        "is_published": true,
        "is_hidden": false,
        "is_expired": false,
        "message": "¡📣 HOY JUEGA EL #EQUIPODELPUEBLO! 💙❤️ 🐿\n\n🏆 Liga del Cercado I Fecha 9\n🆚 Chacarita Jr\n🏟 Estadio Melgar\n▸ HOY\n▸ 8:20a.m.\n\n#ligadearequipa #fbcpierola #azulgrana #ardillasdelpierola",
        "permalink_url": "https://www.facebook.com/337153289263768/posts/426265353685894",
        "from": {
            "name": "FBC Piérola",
            "id": "112828461693258"
        }
    },
    {
        "id": "112828461693258_424398723872557",
        "created_time": "2024-05-01T11:00:35+0000",
        "full_picture": "https://scontent-sjc3-1.xx.fbcdn.net/v/t39.30808-6/438129215_424323860546710_5183748284273078876_n.jpg?stp=dst-jpg_p720x720\u0026_nc_cat=110\u0026ccb=1-7\u0026_nc_sid=5f2048\u0026_nc_ohc=BRWIG3-pq7wQ7kNvgEQj0MR\u0026_nc_ht=scontent-sjc3-1.xx\u0026edm=AJdBtusEAAAA\u0026oh=00_AfD3tpkkJlr7CgboSTW47hGb6ZdU_QzUtwIHlNafW4jstQ\u0026oe=663F66AF",
        "is_popular": false,
        "is_published": true,
        "is_hidden": false,
        "is_expired": false,
        "message": "En este día especial, rendimos honor a nuestra Virgencita de Chapi, símbolo de devoción y esperanza para todo Arequipeño 🗻. Que su amor y protección sigan iluminando nuestros caminos ♱🤍\n\n#Arequipa #FBCPiérola #1deMayo #VirgenDeChapi",
        "permalink_url": "https://www.facebook.com/337153289263768/posts/424398723872557",
        "from": {
            "name": "FBC Piérola",
            "id": "112828461693258"
        }
    },
    {
        "id": "112828461693258_421856030793493",
        "created_time": "2024-04-27T19:59:18+0000",
        "full_picture": "https://scontent-sjc3-1.xx.fbcdn.net/v/t39.30808-6/440785918_421855760793520_4990173933561888956_n.jpg?stp=dst-jpg_p720x720\u0026_nc_cat=101\u0026ccb=1-7\u0026_nc_sid=5f2048\u0026_nc_ohc=sn8SUgwv0bcQ7kNvgG1wY5y\u0026_nc_ht=scontent-sjc3-1.xx\u0026edm=AJdBtusEAAAA\u0026oh=00_AfAhwkL4bh3VzsZff8C2xqiwAsvcWiMljnfESC1db17qKw\u0026oe=663F69AF",
        "is_popular": false,
        "is_published": true,
        "is_hidden": false,
        "is_expired": false,
        "message": "▸ FINAL DEL PARTIDO ⏰\n\n📌 #FBCPiérola 0 - 2 #WhiteStar\n🏆 Liga del Cercado I Fecha 8\n\nA seguir trabajando Azulgranas ❤💙💪🏼\n\n#ligadearequipa #fbcpierola #azulgrana #ardillasdelpierola",
        "permalink_url": "https://www.facebook.com/337153289263768/posts/421856030793493",
        "from": {
            "name": "FBC Piérola",
            "id": "112828461693258"
        }
    },
    {
        "id": "112828461693258_421783737467389",
        "created_time": "2024-04-27T17:30:07+0000",
        "full_picture": "https://scontent-sjc3-1.xx.fbcdn.net/v/t39.30808-6/440478190_421535687492194_5592851401961069378_n.jpg?stp=dst-jpg_p720x720\u0026_nc_cat=109\u0026ccb=1-7\u0026_nc_sid=5f2048\u0026_nc_ohc=aWkIl5Q5ZxYQ7kNvgHhIMhW\u0026_nc_ht=scontent-sjc3-1.xx\u0026edm=AJdBtusEAAAA\u0026oh=00_AfC1ibypjCHNMrTA7p4mVOvIIA1i9wU5FajPUPFDqpoM7w\u0026oe=663F695F",
        "is_popular": false,
        "is_published": true,
        "is_hidden": false,
        "is_expired": false,
        "message": "📣 ¡ARRANCAMOS EL PARTIDO!\n¡🐿 VAMOS AZULGRANAS! ❤💙\n\n#ligadearequipa #fbcpierola #azulgrana #ardillasdelpierola",
        "permalink_url": "https://www.facebook.com/337153289263768/posts/421783737467389",
        "from": {
            "name": "FBC Piérola",
            "id": "112828461693258"
        }
    },
    {
        "id": "112828461693258_421561807489582",
        "created_time": "2024-04-27T11:00:17+0000",
        "full_picture": "https://scontent-sjc3-1.xx.fbcdn.net/v/t39.30808-6/440113732_421474994164930_7091964745995402679_n.jpg?stp=dst-jpg_p720x720\u0026_nc_cat=107\u0026ccb=1-7\u0026_nc_sid=5f2048\u0026_nc_ohc=FTpyHd01yrYQ7kNvgEQ3ULV\u0026_nc_ht=scontent-sjc3-1.xx\u0026edm=AJdBtusEAAAA\u0026oh=00_AfDkOzGC8uu1bBnV1rVMxAAQGO94aRHyeViYT_6jcHG1ww\u0026oe=663F6A16",
        "is_popular": false,
        "is_published": true,
        "is_hidden": false,
        "is_expired": false,
        "message": "¡📣 HOY JUEGA EL #EQUIPODELPUEBLO! 💙❤️ 🐿\n\n🏆 Liga del Cercado I Fecha 8\n🆚 White Star\n🏟 Estadio Melgar\n▸ HOY\n▸ 12:30p.m.\n\n#ligadearequipa #fbcpierola #azulgrana #ardillasdelpierola",
        "permalink_url": "https://www.facebook.com/337153289263768/posts/421561807489582",
        "from": {
            "name": "FBC Piérola",
            "id": "112828461693258"
        }
    },
    {
        "id": "112828461693258_417152274597202",
        "created_time": "2024-04-20T21:39:35+0000",
        "full_picture": "https://scontent-sjc3-1.xx.fbcdn.net/v/t39.30808-6/439832217_417151841263912_3297159701510690157_n.jpg?stp=dst-jpg_p720x720\u0026_nc_cat=109\u0026ccb=1-7\u0026_nc_sid=5f2048\u0026_nc_ohc=HeX8fkMQNdcQ7kNvgG3-07Q\u0026_nc_ht=scontent-sjc3-1.xx\u0026edm=AJdBtusEAAAA\u0026oh=00_AfC9wgVPNfhIHA0fJ8asBF5A-SAnxRPjbAn5sng6W0weRQ\u0026oe=663F6589",
        "is_popular": false,
        "is_published": true,
        "is_hidden": false,
        "is_expired": false,
        "message": "▸ FINAL DEL PARTIDO ⏰\n\n📌 #FBCPiérola 0 - 3 #SportivoHuracán \n🏆 Liga del Cercado I Fecha 7\n\nA seguir trabajando Azulgranas ❤💙💪🏼\n\n#ligadearequipa #fbcpierola #azulgrana #ardillasdelpierola",
        "permalink_url": "https://www.facebook.com/337153289263768/posts/417152274597202",
        "from": {
            "name": "FBC Piérola",
            "id": "112828461693258"
        }
    },
    {
        "id": "112828461693258_417103041268792",
        "created_time": "2024-04-20T19:30:05+0000",
        "full_picture": "https://scontent-sjc3-1.xx.fbcdn.net/v/t39.30808-6/438790292_417093474603082_6447108723697571053_n.jpg?stp=dst-jpg_p720x720\u0026_nc_cat=105\u0026ccb=1-7\u0026_nc_sid=5f2048\u0026_nc_ohc=nVdQGIgTsSAQ7kNvgEijCxk\u0026_nc_ht=scontent-sjc3-1.xx\u0026edm=AJdBtusEAAAA\u0026oh=00_AfC1CAUyXEKAFfLTyk9BP2uJV5PV4v0iHSFcK2nCdFvozg\u0026oe=663F5CF3",
        "is_popular": false,
        "is_published": true,
        "is_hidden": false,
        "is_expired": false,
        "message": "📣 ¡ARRANCAMOS EL PARTIDO!\n¡🐿 VAMOS AZULGRANAS! ❤💙\n\n#ligadearequipa #fbcpierola #azulgrana #ardillasdelpierola",
        "permalink_url": "https://www.facebook.com/337153289263768/posts/417103041268792",
        "from": {
            "name": "FBC Piérola",
            "id": "112828461693258"
        }
    },
    {
        "id": "112828461693258_416849121294184",
        "created_time": "2024-04-20T11:00:12+0000",
        "full_picture": "https://scontent-sjc3-1.xx.fbcdn.net/v/t39.30808-6/438742422_416764871302609_3669075048199920152_n.jpg?stp=dst-jpg_p720x720\u0026_nc_cat=109\u0026ccb=1-7\u0026_nc_sid=5f2048\u0026_nc_ohc=JTvyzVW2JVwQ7kNvgERIPqV\u0026_nc_ht=scontent-sjc3-1.xx\u0026edm=AJdBtusEAAAA\u0026oh=00_AfCiCfjIBqKFALktVXS7lthcGlV8yIKMTep33c0kqavQlQ\u0026oe=663F38A7",
        "is_popular": false,
        "is_published": true,
        "is_hidden": false,
        "is_expired": false,
        "message": "¡📣 HOY JUEGA EL #EQUIPODELPUEBLO! 💙❤️ 🐿\n\n🏆 Liga del Cercado I Fecha 7\n🆚 Sportivo Huracán\n🏟 Estadio Melgar\n▸ HOY\n▸ 02:30p.m.\n\n#ligadearequipa #fbcpierola #azulgrana #ardillasdelpierola #clásico",
        "permalink_url": "https://www.facebook.com/337153289263768/posts/416849121294184",
        "from": {
            "name": "FBC Piérola",
            "id": "112828461693258"
        }
    },
    {
        "id": "112828461693258_412444478401315",
        "created_time": "2024-04-13T15:23:33+0000",
        "full_picture": "https://scontent-sjc3-1.xx.fbcdn.net/v/t39.30808-6/436210627_412443748401388_1201142468707671909_n.jpg?stp=dst-jpg_p720x720\u0026_nc_cat=101\u0026ccb=1-7\u0026_nc_sid=5f2048\u0026_nc_ohc=AT1AWIyLBJwQ7kNvgEqx-ti\u0026_nc_ht=scontent-sjc3-1.xx\u0026edm=AJdBtusEAAAA\u0026oh=00_AfAq8BXRBYfafMhak3xJ3xzilt5-DG55ondxUTup8TmOiQ\u0026oe=663F5042",
        "is_popular": false,
        "is_published": true,
        "is_hidden": false,
        "is_expired": false,
        "message": "▸ FINAL DEL PARTIDO ⏰\n\n📌 #FBCPiérola 2 - 2 #ArequipaFBC\n🏆 Liga del Cercado I Fecha 6\n\nA seguir trabajando Azulgranas ❤💙💪🏼\n\n#ligadearequipa #fbcpierola #azulgrana #ardillasdelpierola",
        "permalink_url": "https://www.facebook.com/337153289263768/posts/412444478401315",
        "from": {
            "name": "FBC Piérola",
            "id": "112828461693258"
        }
    },
    {
        "id": "112828461693258_412378145074615",
        "created_time": "2024-04-13T13:20:07+0000",
        "full_picture": "https://scontent-sjc3-1.xx.fbcdn.net/v/t39.30808-6/435688577_412244385087991_4295763946939927658_n.jpg?stp=dst-jpg_p720x720\u0026_nc_cat=101\u0026ccb=1-7\u0026_nc_sid=5f2048\u0026_nc_ohc=JKkYhRM5UJgQ7kNvgH4_ZTd\u0026_nc_ht=scontent-sjc3-1.xx\u0026edm=AJdBtusEAAAA\u0026oh=00_AfDED1mWDTr4RjwBxXGn1aD15Czd-rQs8XeWB1WA6jqQ7w\u0026oe=663F4873",
        "is_popular": false,
        "is_published": true,
        "is_hidden": false,
        "is_expired": false,
        "message": "📣 ¡ARRANCAMOS EL PARTIDO!\n¡🐿 VAMOS AZULGRANAS! ❤💙\n\n#ligadearequipa #fbcpierola #azulgrana #ardillasdelpierola",
        "permalink_url": "https://www.facebook.com/337153289263768/posts/412378145074615",
        "from": {
            "name": "FBC Piérola",
            "id": "112828461693258"
        }
    },
    {
        "id": "112828461693258_412162748429488",
        "created_time": "2024-04-13T05:16:41+0000",
        "full_picture": "https://scontent-sjc3-1.xx.fbcdn.net/v/t39.30808-6/436096814_412162231762873_2222949754137357560_n.jpg?stp=dst-jpg_p720x720\u0026_nc_cat=111\u0026ccb=1-7\u0026_nc_sid=5f2048\u0026_nc_ohc=zzDVJUCMFc0Q7kNvgEGipbD\u0026_nc_ht=scontent-sjc3-1.xx\u0026edm=AJdBtusEAAAA\u0026oh=00_AfDLXajumsgphd2d9a-N7ZZjXs8RYrD78vnPfu2M74KlzQ\u0026oe=663F4F54",
        "is_popular": false,
        "is_published": true,
        "is_hidden": false,
        "is_expired": false,
        "message": "¡📣 HOY JUEGA EL #EQUIPODELPUEBLO! 💙❤️ 🐿\n\n🏆 Liga del Cercado I Fecha 6\n🆚 Arequipa FBC\n🏟 Estadio Melgar\n▸ HOY\n▸ 08:20a.m.\n\n#ligadearequipa #fbcpierola #azulgrana #ardillasdelpierola",
        "permalink_url": "https://www.facebook.com/337153289263768/posts/412162748429488",
        "from": {
            "name": "FBC Piérola",
            "id": "112828461693258"
        }
    },
    {
        "id": "112828461693258_407944805517949",
        "created_time": "2024-04-06T21:55:43+0000",
        "full_picture": "https://scontent-sjc3-1.xx.fbcdn.net/v/t39.30808-6/436186054_407942052184891_7575945218823875021_n.jpg?stp=dst-jpg_p720x720\u0026_nc_cat=100\u0026ccb=1-7\u0026_nc_sid=5f2048\u0026_nc_ohc=hNR0Vl2YxHgQ7kNvgE4Y5fh\u0026_nc_ht=scontent-sjc3-1.xx\u0026edm=AJdBtusEAAAA\u0026oh=00_AfBL8g08ad-kqp8uUASOOQYyFBLRmEKP_Bw8HVJqIm2kfg\u0026oe=663F47AD",
        "is_popular": false,
        "is_published": true,
        "is_hidden": false,
        "is_expired": false,
        "message": "▸ FINAL DEL PARTIDO ⏰\n\n📌 #FBCPiérola 1 - 2 #ADCantolao\n🏆  Liga del Cercado I Fecha 5\n\nA seguir trabajando Azulgranas ❤💙💪🏼\n\n  #ligadearequipa #fbcpierola #azulgrana #ardillasdelpierola",
        "permalink_url": "https://www.facebook.com/337153289263768/posts/407944805517949",
        "from": {
            "name": "FBC Piérola",
            "id": "112828461693258"
        }
    },
    {
        "id": "112828461693258_407917572187339",
        "created_time": "2024-04-06T20:47:59+0000",
        "full_picture": "https://scontent-sjc3-1.xx.fbcdn.net/v/t15.5256-10/408916657_389287954073551_1310596671653263295_n.jpg?stp=dst-jpg_p843x403\u0026_nc_cat=107\u0026ccb=1-7\u0026_nc_sid=5f2048\u0026_nc_ohc=uYOiQHGDBD8Q7kNvgHGwAsA\u0026_nc_ht=scontent-sjc3-1.xx\u0026edm=AJdBtusEAAAA\u0026oh=00_AfAGWBFa_i0Uqe1ccvJBZJx0zVpHIk1ZtOOcsiXmk5mASA\u0026oe=663F498E",
        "is_popular": false,
        "is_published": true,
        "is_hidden": false,
        "is_expired": false,
        "message": "",
        "permalink_url": "https://www.facebook.com/337153289263768/posts/407917572187339",
        "from": {
            "name": "FBC Piérola",
            "id": "112828461693258"
        }
    },
    {
        "id": "112828461693258_407884568857306",
        "created_time": "2024-04-06T19:30:09+0000",
        "full_picture": "https://scontent-sjc3-1.xx.fbcdn.net/v/t39.30808-6/435690724_407695182209578_6603366109886593936_n.jpg?stp=dst-jpg_p720x720\u0026_nc_cat=110\u0026ccb=1-7\u0026_nc_sid=5f2048\u0026_nc_ohc=U9vhfvi14nAQ7kNvgEsFZY1\u0026_nc_ht=scontent-sjc3-1.xx\u0026edm=AJdBtusEAAAA\u0026oh=00_AfA3ORl3V_AnxNZKUh0MXjtOh1poyFNHl5R95bJoUSda5A\u0026oe=663F584F",
        "is_popular": false,
        "is_published": true,
        "is_hidden": false,
        "is_expired": false,
        "message": "📣 ¡ARRANCAMOS EL PARTIDO!\n¡🐿 VAMOS AZULGRANAS! ❤💙\n\n#ligadearequipa #fbcpierola #azulgrana #ardillasdelpierola",
        "permalink_url": "https://www.facebook.com/337153289263768/posts/407884568857306",
        "from": {
            "name": "FBC Piérola",
            "id": "112828461693258"
        }
    },
    {
        "id": "112828461693258_407642798881483",
        "created_time": "2024-04-06T12:00:22+0000",
        "full_picture": "https://scontent-sjc3-1.xx.fbcdn.net/v/t39.30808-6/434277543_407503565562073_1506793932694148421_n.jpg?stp=dst-jpg_p720x720\u0026_nc_cat=103\u0026ccb=1-7\u0026_nc_sid=5f2048\u0026_nc_ohc=BYAKia_r6vQQ7kNvgGvZZ1c\u0026_nc_ht=scontent-sjc3-1.xx\u0026edm=AJdBtusEAAAA\u0026oh=00_AfDPnV7IseOwPB3NhLRB4eqcSw_Pgkv9ow0FRYZBZHqX0w\u0026oe=663F3853",
        "is_popular": false,
        "is_published": true,
        "is_hidden": false,
        "is_expired": false,
        "message": "¡📣 HOY JUEGA EL #EQUIPODELPUEBLO! 💙❤️ 🐿\n\n🏆 Liga del Cercado I Fecha 5\n🆚 AD Cantolao\n🏟 Estadio Melgar\n▸ HOY\n▸ 02:30p.m.\n\n#ligadearequipa #fbcpierola #azulgrana #ardillasdelpierola",
        "permalink_url": "https://www.facebook.com/337153289263768/posts/407642798881483",
        "from": {
            "name": "FBC Piérola",
            "id": "112828461693258"
        }
    },
    {
        "id": "112828461693258_403072872671809",
        "created_time": "2024-03-30T17:38:33+0000",
        "full_picture": "https://scontent-sjc3-1.xx.fbcdn.net/v/t39.30808-6/434190382_403069369338826_2968023454692873905_n.jpg?stp=dst-jpg_p720x720\u0026_nc_cat=104\u0026ccb=1-7\u0026_nc_sid=5f2048\u0026_nc_ohc=KwDtOGlm7vkQ7kNvgGFGYxN\u0026_nc_ht=scontent-sjc3-1.xx\u0026edm=AJdBtusEAAAA\u0026oh=00_AfCFYpVJYLMWTRyYzp9vc48cjNcTSorCUKd_RM1E1dQBgg\u0026oe=663F46C5",
        "is_popular": false,
        "is_published": true,
        "is_hidden": false,
        "is_expired": false,
        "message": "CON UN CONTUNDENTE RESULTADO EN EL MARCADOR, LOS 3pts SE QUEDAN FINALMENTE CON EL EQUIPO DEL PUEBLO 💙❤️🐿 #VamosPiérola \n\n#ligadearequipa #fbcpierola #azulgrana #ardillasdelpierola",
        "permalink_url": "https://www.facebook.com/337153289263768/posts/403072872671809",
        "from": {
            "name": "FBC Piérola",
            "id": "112828461693258"
        }
    },
    {
        "id": "112828461693258_403006536011776",
        "created_time": "2024-03-30T15:30:06+0000",
        "full_picture": "https://scontent-sjc3-1.xx.fbcdn.net/v/t39.30808-6/432946314_402838849361878_7619480804108231665_n.jpg?stp=dst-jpg_p720x720\u0026_nc_cat=111\u0026ccb=1-7\u0026_nc_sid=5f2048\u0026_nc_ohc=X3KkIXMOXocQ7kNvgE6IKQY\u0026_nc_ht=scontent-sjc3-1.xx\u0026edm=AJdBtusEAAAA\u0026oh=00_AfChSmyB6RLqnBioYlNWiMDN2ZiEqvLUzFEJlK20YkD9cA\u0026oe=663F429B",
        "is_popular": false,
        "is_published": true,
        "is_hidden": false,
        "is_expired": false,
        "message": "📣 ¡ARRANCAMOS EL PARTIDO!\n¡🐿 VAMOS AZULGRANAS! ❤💙\n\n#ligadearequipa #fbcpierola #azulgrana #ardillasdelpierola",
        "permalink_url": "https://www.facebook.com/337153289263768/posts/403006536011776",
        "from": {
            "name": "FBC Piérola",
            "id": "112828461693258"
        }
    },
    {
        "id": "112828461693258_402863402692756",
        "created_time": "2024-03-30T11:00:31+0000",
        "full_picture": "https://scontent-sjc3-1.xx.fbcdn.net/v/t39.30808-6/434718124_402748942704202_1170662050521323504_n.jpg?stp=dst-jpg_p720x720\u0026_nc_cat=106\u0026ccb=1-7\u0026_nc_sid=5f2048\u0026_nc_ohc=8v4qkUUeRdgQ7kNvgE6VFP_\u0026_nc_ht=scontent-sjc3-1.xx\u0026edm=AJdBtusEAAAA\u0026oh=00_AfCOxAmdiEIOh6QIFOQpcHmsRqSg2ekSNA481ysZnJKhQQ\u0026oe=663F5415",
        "is_popular": false,
        "is_published": true,
        "is_hidden": false,
        "is_expired": false,
        "message": "¡📣 HOY JUEGA EL #EQUIPODELPUEBLO! 💙❤️ 🐿\n\n🏆 Liga del Cercado I Fecha 4\n🆚 Sportivo Huracancito\n🏟 Estadio Melgar \n▸ HOY\n▸ 10:30a.m.\n\n#ligadearequipa #fbcpierola #azulgrana #ardillasdelpierola",
        "permalink_url": "https://www.facebook.com/337153289263768/posts/402863402692756",
        "from": {
            "name": "FBC Piérola",
            "id": "112828461693258"
        }
    },
    {
        "id": "112828461693258_401525352826561",
        "created_time": "2024-03-28T11:33:02+0000",
        "full_picture": "https://scontent-sjc3-1.xx.fbcdn.net/v/t39.30808-6/434375088_831831695656133_6057823840573568463_n.jpg?stp=dst-jpg_p720x720\u0026_nc_cat=102\u0026ccb=1-7\u0026_nc_sid=5f2048\u0026_nc_ohc=6co6iEyealQQ7kNvgH5gvwg\u0026_nc_ht=scontent-sjc3-1.xx\u0026edm=AJdBtusEAAAA\u0026oh=00_AfDOnlXvycOxvXm_3hetuIOiBmbM8WhF4wrbrtp-fO-2yw\u0026oe=663F494C",
        "is_popular": false,
        "is_published": true,
        "is_hidden": false,
        "is_expired": false,
        "message": "",
        "permalink_url": "https://www.facebook.com/337153289263768/posts/401525352826561",
        "from": {
            "name": "FBC Piérola",
            "id": "112828461693258"
        }
    },
    {
        "id": "112828461693258_399556999690063",
        "created_time": "2024-03-25T12:00:28+0000",
        "full_picture": "https://scontent-sjc3-1.xx.fbcdn.net/v/t39.30808-6/434123370_399514276361002_4968933198033787056_n.jpg?stp=dst-jpg_p720x720\u0026_nc_cat=103\u0026ccb=1-7\u0026_nc_sid=5f2048\u0026_nc_ohc=2xSGSctjpmkQ7kNvgFRZ1gY\u0026_nc_ht=scontent-sjc3-1.xx\u0026edm=AJdBtusEAAAA\u0026oh=00_AfDJ_fcv4udG8CHkzW75RxO_GmU-Xd_DDKi61b9sKPFKhQ\u0026oe=663F5769",
        "is_popular": false,
        "is_published": true,
        "is_hidden": false,
        "is_expired": false,
        "message": "El día de hoy queremos extender un ameno y fraternal saludo a nuestro compadre FBC Melgar por sus 🎊 109 AÑOS DE VIDA INSTITUCIONAL 🎊 Sigamos llevando el nombre de Arequipa en lo alto 🗻 ¡Y que sigan los éxitos León 🦁🔴⚫️! \n‎ ‎ \n‎ \n#Arequipa #FBCPiérola #FBCMelgar #Aniversario #SoyArequipeño",
        "permalink_url": "https://www.facebook.com/337153289263768/posts/399556999690063",
        "from": {
            "name": "FBC Piérola",
            "id": "112828461693258"
        }
    },
    {
        "id": "112828461693258_398476976464732",
        "created_time": "2024-03-23T19:46:33+0000",
        "full_picture": "https://scontent-sjc3-1.xx.fbcdn.net/v/t39.30808-6/432767865_398475706464859_7757363558324311850_n.jpg?stp=dst-jpg_p720x720\u0026_nc_cat=109\u0026ccb=1-7\u0026_nc_sid=5f2048\u0026_nc_ohc=b7RmZDzk0TkQ7kNvgFmHW6-\u0026_nc_ht=scontent-sjc3-1.xx\u0026edm=AJdBtusEAAAA\u0026oh=00_AfCqX0_ZZDpQKGibme6rpoWwmhvaOAnWu1d6WNErXbiP8A\u0026oe=663F3CD5",
        "is_popular": false,
        "is_published": true,
        "is_hidden": false,
        "is_expired": false,
        "message": "¡FINAL DEL PARTIDO E IGUALDAD EN EL MARCADOR! TRAS UN PARTIDAZO VIVIDO, NUESTRAS ARDILLAS PUSIERON EL EMPATE Y SE IMPUSIERON EN EL ESTADIO MELGAR 🗻 #VamosPiérola ❤💙🐿\n\n#ligadearequipa #fbcpierola #azulgrana #ardillasdelpierola",
        "permalink_url": "https://www.facebook.com/337153289263768/posts/398476976464732",
        "from": {
            "name": "FBC Piérola",
            "id": "112828461693258"
        }
    },
    {
        "id": "112828461693258_398410759804687",
        "created_time": "2024-03-23T17:30:11+0000",
        "full_picture": "https://scontent-sjc3-1.xx.fbcdn.net/v/t39.30808-6/432768112_398158376496592_7815386395665619692_n.jpg?stp=dst-jpg_p720x720\u0026_nc_cat=100\u0026ccb=1-7\u0026_nc_sid=5f2048\u0026_nc_ohc=kA_IPnPUqPoQ7kNvgH5HPnj\u0026_nc_ht=scontent-sjc3-1.xx\u0026edm=AJdBtusEAAAA\u0026oh=00_AfCVXmW3KVjiJ_tIhqRjEXL9A2YrJGQJ4j0SDuctkjSUng\u0026oe=663F6A6C",
        "is_popular": false,
        "is_published": true,
        "is_hidden": false,
        "is_expired": false,
        "message": "📣 ¡ARRANCAMOS LOS PRIMEROS 45' MIN!\n¡🐿 VAMOS AZULGRANAS! ❤💙\n\n#ligadearequipa #fbcpierola #azulgrana #ardillasdelpierola",
        "permalink_url": "https://www.facebook.com/337153289263768/posts/398410759804687",
        "from": {
            "name": "FBC Piérola",
            "id": "112828461693258"
        }
    },
    {
        "id": "112828461693258_398206379825125",
        "created_time": "2024-03-23T11:00:06+0000",
        "full_picture": "https://scontent-sjc3-1.xx.fbcdn.net/v/t39.30808-6/432876316_398155163163580_6646321512212541913_n.jpg?stp=dst-jpg_p720x720\u0026_nc_cat=100\u0026ccb=1-7\u0026_nc_sid=5f2048\u0026_nc_ohc=V9kNTaCpQ-0Q7kNvgFfRbjz\u0026_nc_ht=scontent-sjc3-1.xx\u0026edm=AJdBtusEAAAA\u0026oh=00_AfAaUPki2j3PP4ZluKR7HdaHI4hjLYz1aauVhjhjcBr1IQ\u0026oe=663F6214",
        "is_popular": false,
        "is_published": true,
        "is_hidden": false,
        "is_expired": false,
        "message": "¡📣 HOY JUEGA EL #EQUIPODELPUEBLO! 💙❤️ 🐿 \n\n🏆 Liga del Cercado I Fecha 3\n🆚 Atlético Universidad\n🏟 Estadio Melgar\n▸ HOY\n▸ 12:30 p.m.\n\n#ligadearequipa #fbcpierola #azulgrana #ardillasdelpierola",
        "permalink_url": "https://www.facebook.com/337153289263768/posts/398206379825125",
        "from": {
            "name": "FBC Piérola",
            "id": "112828461693258"
        }
    }
]