[
    {
        "id": "112828461693258_721865414125885",
        "created_time": "2025-05-29T15:15:28+0000",
        "full_picture": "https://scontent-fra3-2.xx.fbcdn.net/v/t39.30808-6/495261968_1120268746806155_5728217059611695750_n.jpg?stp=dst-jpg_p720x720_tt6\u0026_nc_cat=111\u0026ccb=1-7\u0026_nc_sid=833d8c\u0026_nc_ohc=KOSYcxqWi8QQ7kNvwGF-oVy\u0026_nc_oc=Adl4Ej449CO-oELMPaGEtCzyuj7TiKbN81-e3UoBcvl1mE4e9VIllz78nNKp0oOgSBs\u0026_nc_zt=23\u0026_nc_ht=scontent-fra3-2.xx\u0026edm=AJdBtusEAAAA\u0026_nc_gid=_TuzWreOdTQAGpM8iVY-4g\u0026oh=00_AfMrYrAyidY6x_JTXG_GMzwnYqVfhdfh7gEFiJ7jSYh7IA\u0026oe=684EB09D",
        "is_popular": false,
        "is_published": true,
        "is_hidden": false,
        "is_expired": false,
        "message": "",
        "permalink_url": "https://www.facebook.com/337153289263768/posts/721865414125885",
        "from": {
            "name": "FBC Piérola",
            "id": "112828461693258"
        }
    },
    {
        "id": "112828461693258_721865327459227",
        "created_time": "2025-05-29T15:15:22+0000",
        "full_picture": "https://scontent-fra5-2.xx.fbcdn.net/v/t39.30808-6/495571769_1599696487546899_7279692098355596360_n.jpg?stp=dst-jpg_p720x720_tt6\u0026_nc_cat=109\u0026ccb=1-7\u0026_nc_sid=127cfc\u0026_nc_ohc=7ybL22m28gQQ7kNvwH4rrVi\u0026_nc_oc=AdliBOWSIckSog99crshyvtpSEcUgfdtz6HcHNP6Pkpvkvcaj1ft4mJ9OgvGLxMRNlw\u0026_nc_zt=23\u0026_nc_ht=scontent-fra5-2.xx\u0026edm=AJdBtusEAAAA\u0026_nc_gid=_TuzWreOdTQAGpM8iVY-4g\u0026oh=00_AfOF6zWdRWlC9JPL1zY2bP5paw5N7MDtaP2k6o2PCt8b1A\u0026oe=684EB10F",
        "is_popular": false,
        "is_published": true,
        "is_hidden": false,
        "is_expired": false,
        "message": "",
        "permalink_url": "https://www.facebook.com/337153289263768/posts/721865327459227",
        "from": {
            "name": "FBC Piérola",
            "id": "112828461693258"
        }
    },
    {
        "id": "112828461693258_721865284125898",
        "created_time": "2025-05-29T15:15:17+0000",
        "full_picture": "https://scontent-fra3-1.xx.fbcdn.net/v/t15.5256-10/495001481_1001754502151896_5144358049096825090_n.jpg?_nc_cat=108\u0026ccb=1-7\u0026_nc_sid=282d23\u0026_nc_ohc=_FQY6im80-4Q7kNvwF2BXxW\u0026_nc_oc=AdlLmVASd-6kIFeXOz12dfnxiDi3B49_-G7asUHjn59wJlCXhGNNb7gqySp4r1h8aqM\u0026_nc_zt=23\u0026_nc_ht=scontent-fra3-1.xx\u0026edm=AJdBtusEAAAA\u0026_nc_gid=_TuzWreOdTQAGpM8iVY-4g\u0026oh=00_AfPcif-SuCbL1JYX6lqcTC8wkHtU_oNdggir_VlgUWly8Q\u0026oe=684EC300",
        "is_popular": false,
        "is_published": true,
        "is_hidden": false,
        "is_expired": false,
        "message": "",
        "permalink_url": "https://www.facebook.com/337153289263768/posts/721865284125898",
        "from": {
            "name": "FBC Piérola",
            "id": "112828461693258"
        }
    },
    {
        "id": "112828461693258_705621852416908",
        "created_time": "2025-05-07T13:32:15+0000",
        "full_picture": "https://scontent-fra5-1.xx.fbcdn.net/v/t39.30808-6/494549132_705621825750244_6163441404195276690_n.jpg?stp=dst-jpg_p720x720_tt6\u0026_nc_cat=110\u0026ccb=1-7\u0026_nc_sid=127cfc\u0026_nc_ohc=gb-5VD0j7CkQ7kNvwGLuESj\u0026_nc_oc=AdnFZBXUAK0TQRkFccU1Ud_EA-6ls2iP7BRFphBfdDdUt8f5tIORInm6Fey_i5l_AQw\u0026_nc_zt=23\u0026_nc_ht=scontent-fra5-1.xx\u0026edm=AJdBtusEAAAA\u0026_nc_gid=_TuzWreOdTQAGpM8iVY-4g\u0026oh=00_AfN8jSd4CEa_GFj566_LShxF8nhnOmmywdGWuMYCLnD88w\u0026oe=684EA8B9",
        "is_popular": false,
        "is_published": true,
        "is_hidden": false,
        "is_expired": false,
        "message": "Feliz 103 aniversario familia azulgrana, hoy tenemos sesión solemne. Abrazos ⚽️⚽️⚽️⚽️⚽️⚽️",
        "permalink_url": "https://www.facebook.com/337153289263768/posts/705621852416908",
        "from": {
            "name": "FBC Piérola",
            "id": "112828461693258"
        }
    },
    {
        "id": "112828461693258_689783670667393",
        "created_time": "2025-04-17T16:36:38+0000",
        "full_picture": "https://scontent-fra3-1.xx.fbcdn.net/v/t39.30808-6/489957115_689782657334161_7357037498916983196_n.jpg?_nc_cat=103\u0026ccb=1-7\u0026_nc_sid=833d8c\u0026_nc_ohc=VADooT73jDYQ7kNvwHu-8qs\u0026_nc_oc=AdnXvkOqYy09_TTbUxxIl44mFedaVFyAoMS5o7_NjlclWycwuK4MWyhXlT6bsised8Q\u0026_nc_zt=23\u0026_nc_ht=scontent-fra3-1.xx\u0026edm=AJdBtusEAAAA\u0026_nc_gid=_TuzWreOdTQAGpM8iVY-4g\u0026oh=00_AfNpJBVOEPfX8o2Rfdb7Q3iJt_CAIj2DfSkhb8XF-xhKww\u0026oe=684ECA3A",
        "is_popular": false,
        "is_published": true,
        "is_hidden": false,
        "is_expired": false,
        "message": "La familia azulgrana está de duelo, nuestro Past presidente el Ing Edgar Llamoca Téllez falleció en nuestra tierra Arequipa. Expresamos condolencias a sus hijas nietos y familia. QEPD y QDDG 🙏🙏🙏🙏🙏",
        "permalink_url": "https://www.facebook.com/337153289263768/posts/689783670667393",
        "from": {
            "name": "FBC Piérola",
            "id": "112828461693258"
        }
    },
    {
        "id": "112828461693258_667911362854624",
        "created_time": "2025-03-22T20:21:16+0000",
        "full_picture": "",
        "is_popular": false,
        "is_published": true,
        "is_hidden": false,
        "is_expired": false,
        "message": "",
        "permalink_url": "https://www.facebook.com/337153289263768/posts/667911362854624",
        "from": {
            "name": "FBC Piérola",
            "id": "112828461693258"
        }
    },
    {
        "id": "112828461693258_651108077868286",
        "created_time": "2025-03-02T14:16:51+0000",
        "full_picture": "https://scontent-fra3-1.xx.fbcdn.net/v/t39.30808-6/487039992_650251414657593_8759834444562998655_n.jpg?stp=cp1_dst-jpg_p720x720_tt6\u0026_nc_cat=105\u0026ccb=1-7\u0026_nc_sid=833d8c\u0026_nc_ohc=4bKOqdyEB_UQ7kNvwFCJMG0\u0026_nc_oc=AdmNAVAR6sE4dD-HW4QFNxp-GhJqKoFDbdthyohVTK7I_lMQzu6cQTwSq1PDVP3Orhs\u0026_nc_zt=23\u0026_nc_ht=scontent-fra3-1.xx\u0026edm=AJdBtusEAAAA\u0026_nc_gid=_TuzWreOdTQAGpM8iVY-4g\u0026oh=00_AfO3CpsaxiqVEytZNgnzttwsvz0LmJwx11tB7r_Nih0JOQ\u0026oe=684EAA18",
        "is_popular": false,
        "is_published": true,
        "is_hidden": false,
        "is_expired": false,
        "message": "",
        "permalink_url": "https://www.facebook.com/337153289263768/posts/651108077868286",
        "from": {
            "name": "FBC Piérola",
            "id": "112828461693258"
        }
    },
    {
        "id": "112828461693258_651108034534957",
        "created_time": "2025-03-02T14:16:48+0000",
        "full_picture": "https://scontent-fra5-1.xx.fbcdn.net/v/t39.30808-6/488868702_1100087815469475_1623067226556422660_n.jpg?stp=dst-jpg_p720x720_tt6\u0026_nc_cat=102\u0026ccb=1-7\u0026_nc_sid=833d8c\u0026_nc_ohc=LfwynQdVNggQ7kNvwE_5r0j\u0026_nc_oc=AdlRpOCkprdb1Xl5mOatT7tkROsmyEfPeRpTx6qLMLEsz1JgRz_gl7ULl0G7qDDWyAM\u0026_nc_zt=23\u0026_nc_ht=scontent-fra5-1.xx\u0026edm=AJdBtusEAAAA\u0026_nc_gid=_TuzWreOdTQAGpM8iVY-4g\u0026oh=00_AfMyVcvHP_6NqmfLE-2oSGyD_nyEsICIEjic0M8g7jCYng\u0026oe=684EA330",
        "is_popular": false,
        "is_published": true,
        "is_hidden": false,
        "is_expired": false,
        "message": "",
        "permalink_url": "https://www.facebook.com/337153289263768/posts/651108034534957",
        "from": {
            "name": "FBC Piérola",
            "id": "112828461693258"
        }
    },
    {
        "id": "112828461693258_651107911201636",
        "created_time": "2025-03-02T14:16:36+0000",
        "full_picture": "https://scontent-fra3-1.xx.fbcdn.net/v/t15.5256-10/481857080_1854438162008370_7662729751779857274_n.jpg?_nc_cat=101\u0026ccb=1-7\u0026_nc_sid=282d23\u0026_nc_ohc=CkeKb4NC5nAQ7kNvwHLXY9t\u0026_nc_oc=AdlS2vDBupHct0LmJrndhpe9r0CE5vueGpiZ34_NkkG4IItUXFpKY5HjaegfL2hubIo\u0026_nc_zt=23\u0026_nc_ht=scontent-fra3-1.xx\u0026edm=AJdBtusEAAAA\u0026_nc_gid=_TuzWreOdTQAGpM8iVY-4g\u0026oh=00_AfNp55ULF0vX_hM30DFX6QAfVdI7uLz3rSuvRxCfnztxkg\u0026oe=684EB84E",
        "is_popular": false,
        "is_published": true,
        "is_hidden": false,
        "is_expired": false,
        "message": "",
        "permalink_url": "https://www.facebook.com/337153289263768/posts/651107911201636",
        "from": {
            "name": "FBC Piérola",
            "id": "112828461693258"
        }
    },
    {
        "id": "112828461693258_612685641710530",
        "created_time": "2025-01-12T19:17:29+0000",
        "full_picture": "https://scontent-fra5-1.xx.fbcdn.net/v/t39.30808-6/482025638_657207650591662_4444050076261294253_n.jpg?stp=dst-jpg_p720x720_tt6\u0026_nc_cat=102\u0026ccb=1-7\u0026_nc_sid=833d8c\u0026_nc_ohc=vwJ77ndBnMMQ7kNvwHeOEzX\u0026_nc_oc=Adk595hHvzxfWISyHK29lOx4J9ZxkEVOrMkRvch5PkNuOvwRJcXPxxXjtnAe3LpzZ68\u0026_nc_zt=23\u0026_nc_ht=scontent-fra5-1.xx\u0026edm=AJdBtusEAAAA\u0026_nc_gid=_TuzWreOdTQAGpM8iVY-4g\u0026oh=00_AfPVN4y0vQYe_V2c3No-Whao4xiavJjY9twCxIF3NNc5SQ\u0026oe=684EA661",
        "is_popular": false,
        "is_published": true,
        "is_hidden": false,
        "is_expired": false,
        "message": "Feliz aniversario Club Sportivo Huracán 🥳🥳🥳🥳",
        "permalink_url": "https://www.facebook.com/337153289263768/posts/612685641710530",
        "from": {
            "name": "FBC Piérola",
            "id": "112828461693258"
        }
    },
    {
        "id": "112828461693258_598783053100789",
        "created_time": "2024-12-25T09:35:31+0000",
        "full_picture": "",
        "is_popular": false,
        "is_published": true,
        "is_hidden": false,
        "is_expired": false,
        "message": "friends brothers, let's have a nice good night and a better day than ever\nNativity of the divine child Jesus Christ the King🙏🙏🙏🙏🙏🙏the family gathered greeting the most loved ones and friends near and far.                                                           Linda noche buena, mejor día de la Natividad de Jesús Cristo Rey. Abraxos amig@s y  bendiciones 🙏🙏🙏🙏🙏",
        "permalink_url": "https://www.facebook.com/337153289263768/posts/598783053100789",
        "from": {
            "name": "FBC Piérola",
            "id": "112828461693258"
        }
    },
    {
        "id": "112828461693258_598609593118135",
        "created_time": "2024-12-25T03:59:49+0000",
        "full_picture": "https://scontent-fra5-1.xx.fbcdn.net/v/t39.30808-6/482208549_657016047277489_6245918303913230899_n.jpg?stp=dst-jpg_p720x720_tt6\u0026_nc_cat=102\u0026ccb=1-7\u0026_nc_sid=833d8c\u0026_nc_ohc=55z35ahHeyUQ7kNvwFwIBM2\u0026_nc_oc=AdmEqFWyvVHDvr6Oi2d97pc9eq6YulCW1cJwTvG1A-MKQOB56MR9KoLqxoo9MrAP3a0\u0026_nc_zt=23\u0026_nc_ht=scontent-fra5-1.xx\u0026edm=AJdBtusEAAAA\u0026_nc_gid=_TuzWreOdTQAGpM8iVY-4g\u0026oh=00_AfPWx4oNyS81bCWK5uF2vznbigYlcuz6V_HB5DFq_6q7ng\u0026oe=684EB67C",
        "is_popular": false,
        "is_published": true,
        "is_hidden": false,
        "is_expired": false,
        "message": "",
        "permalink_url": "https://www.facebook.com/337153289263768/posts/598609593118135",
        "from": {
            "name": "FBC Piérola",
            "id": "112828461693258"
        }
    },
    {
        "id": "112828461693258_593936733585421",
        "created_time": "2024-12-18T23:23:21+0000",
        "full_picture": "https://scontent-fra3-1.xx.fbcdn.net/v/t39.30808-6/482327062_656287304017030_5376681293978393218_n.jpg?stp=dst-jpg_p720x720_tt6\u0026_nc_cat=105\u0026ccb=1-7\u0026_nc_sid=833d8c\u0026_nc_ohc=RdpWe6D7DoIQ7kNvwHP7ysP\u0026_nc_oc=AdnNe_ezXF2fHET9WoK4duyUMcGQRaMYb9QszyIBDHlzemw-ctMjXxyrQOyZxMb1n9k\u0026_nc_zt=23\u0026_nc_ht=scontent-fra3-1.xx\u0026edm=AJdBtusEAAAA\u0026_nc_gid=_TuzWreOdTQAGpM8iVY-4g\u0026oh=00_AfO8xJfTJSrP75kGS6sIb0dCHIYUM9KecSS8LH6Moz3aXw\u0026oe=684EAAD9",
        "is_popular": false,
        "is_published": true,
        "is_hidden": false,
        "is_expired": false,
        "message": "",
        "permalink_url": "https://www.facebook.com/337153289263768/posts/593936733585421",
        "from": {
            "name": "FBC Piérola",
            "id": "112828461693258"
        }
    },
    {
        "id": "112828461693258_580505774928517",
        "created_time": "2024-11-30T18:02:33+0000",
        "full_picture": "https://scontent-fra5-2.xx.fbcdn.net/v/t15.5256-10/468339432_1697561487477556_5141256141943449268_n.jpg?_nc_cat=106\u0026ccb=1-7\u0026_nc_sid=032300\u0026_nc_ohc=-vkcnGylodoQ7kNvwFhulJJ\u0026_nc_oc=AdmGCUAycaHurFzD3P4RFPQGMGTtN-pwTbvAuB5JDEUv3kztEMLkvQr0MzPAuqShQBA\u0026_nc_zt=23\u0026_nc_ht=scontent-fra5-2.xx\u0026edm=AJdBtusEAAAA\u0026_nc_gid=_TuzWreOdTQAGpM8iVY-4g\u0026oh=00_AfNTgVZQ-ZiZCn_7FAKEEs0rq-CmVQgj9Tm8u8SdxI9wSg\u0026oe=684EC0FD",
        "is_popular": false,
        "is_published": true,
        "is_hidden": false,
        "is_expired": false,
        "message": "",
        "permalink_url": "https://www.facebook.com/337153289263768/posts/580505774928517",
        "from": {
            "name": "FBC Piérola",
            "id": "112828461693258"
        }
    },
    {
        "id": "112828461693258_491024163876679",
        "created_time": "2024-08-06T20:19:58+0000",
        "full_picture": "https://scontent-fra3-1.xx.fbcdn.net/v/t15.5256-10/454364525_1010439430777047_3901412282573346278_n.jpg?_nc_cat=101\u0026ccb=1-7\u0026_nc_sid=032300\u0026_nc_ohc=RoJQR2KnGRsQ7kNvwFJmJvk\u0026_nc_oc=Adn-xNevtlU5muvVbmVfwC9kQanoMF53vovwDTO5sYtq0XOsZc-5fPyfTeK8l-t2DAA\u0026_nc_zt=23\u0026_nc_ht=scontent-fra3-1.xx\u0026edm=AJdBtusEAAAA\u0026_nc_gid=_TuzWreOdTQAGpM8iVY-4g\u0026oh=00_AfOObbJKcVq-Z8eYtTFQnrFNbCj0Z-YAhuW0SLHkaSUAmQ\u0026oe=684EA6BF",
        "is_popular": false,
        "is_published": true,
        "is_hidden": false,
        "is_expired": false,
        "message": "",
        "permalink_url": "https://www.facebook.com/337153289263768/posts/491024163876679",
        "from": {
            "name": "FBC Piérola",
            "id": "112828461693258"
        }
    },
    {
        "id": "112828461693258_475722762073486",
        "created_time": "2024-07-15T14:08:50+0000",
        "full_picture": "",
        "is_popular": false,
        "is_published": true,
        "is_hidden": false,
        "is_expired": false,
        "message": "",
        "permalink_url": "https://www.facebook.com/337153289263768/posts/475722762073486",
        "from": {
            "name": "FBC Piérola",
            "id": "112828461693258"
        }
    },
    {
        "id": "112828461693258_475062505472845",
        "created_time": "2024-07-14T14:09:43+0000",
        "full_picture": "",
        "is_popular": false,
        "is_published": true,
        "is_hidden": false,
        "is_expired": false,
        "message": "",
        "permalink_url": "https://www.facebook.com/337153289263768/posts/475062505472845",
        "from": {
            "name": "FBC Piérola",
            "id": "112828461693258"
        }
    },
    {
        "id": "112828461693258_474530975525998",
        "created_time": "2024-07-13T17:46:09+0000",
        "full_picture": "",
        "is_popular": false,
        "is_published": true,
        "is_hidden": false,
        "is_expired": false,
        "message": "",
        "permalink_url": "https://www.facebook.com/337153289263768/posts/474530975525998",
        "from": {
            "name": "FBC Piérola",
            "id": "112828461693258"
        }
    },
    {
        "id": "112828461693258_469868829325546",
        "created_time": "2024-07-06T18:17:06+0000",
        "full_picture": "https://scontent-fra3-2.xx.fbcdn.net/v/t15.5256-10/450211800_846501827528060_7179031723627703511_n.jpg?_nc_cat=104\u0026ccb=1-7\u0026_nc_sid=032300\u0026_nc_ohc=jKg3xLr32rMQ7kNvwGlOCiu\u0026_nc_oc=Adn5MC97xVBXpCd3_SR9wt8gjh5gqCZUJk5IF5V7m6JADBEe8bp00meZ6JgyRMvWJek\u0026_nc_zt=23\u0026_nc_ht=scontent-fra3-2.xx\u0026edm=AJdBtusEAAAA\u0026_nc_gid=_TuzWreOdTQAGpM8iVY-4g\u0026oh=00_AfMHkGin3oMLRiNo4OUnEjJzNqjNjdQqj7X0b32dz--DzQ\u0026oe=684E954E",
        "is_popular": false,
        "is_published": true,
        "is_hidden": false,
        "is_expired": false,
        "message": "",
        "permalink_url": "https://www.facebook.com/337153289263768/posts/469868829325546",
        "from": {
            "name": "FBC Piérola",
            "id": "112828461693258"
        }
    },
    {
        "id": "112828461693258_450147724630990",
        "created_time": "2024-06-07T23:34:31+0000",
        "full_picture": "https://scontent-fra5-1.xx.fbcdn.net/v/t39.30808-6/481219056_648228474822913_2179914586356972254_n.jpg?stp=dst-jpg_s720x720_tt6\u0026_nc_cat=102\u0026ccb=1-7\u0026_nc_sid=127cfc\u0026_nc_ohc=NJrBAB7rtNoQ7kNvwEjIiNF\u0026_nc_oc=Adn1a54T22JqwemkpqjuIikRDLhs4vWKl84X1nxM8kANBMYnFvx3XwOANH547OJI9N4\u0026_nc_zt=23\u0026_nc_ht=scontent-fra5-1.xx\u0026edm=AJdBtusEAAAA\u0026_nc_gid=_TuzWreOdTQAGpM8iVY-4g\u0026oh=00_AfOZaeZZ3P8LxrTYzkQdT7yMZY-A_kw9HpyNrcgk6-qcFw\u0026oe=684E9BFC",
        "is_popular": false,
        "is_published": true,
        "is_hidden": false,
        "is_expired": false,
        "message": "Queremos saludar afectuosa y cálidamente al Past presidente de nuestro club azulgrana don Ricardo el Curro Muñoz,  quien hoy siete de junio,  se encuentra celebrando un año más de vida 🎂🎉; su liderazgo y compromiso son pilares fundamentales para nuestro crecimiento ⚽ ¡Muchas bendiciones de parte de toda nuestra familia Azulgrana 🗻🎉!\n\n#FBCPiérola #Arequipa",
        "permalink_url": "https://www.facebook.com/337153289263768/posts/450147724630990",
        "from": {
            "name": "FBC Piérola",
            "id": "112828461693258"
        }
    },
    {
        "id": "112828461693258_445128455132917",
        "created_time": "2024-05-31T12:00:33+0000",
        "full_picture": "https://scontent-fra5-2.xx.fbcdn.net/v/t39.30808-6/481069206_648219808157113_8169081322689613184_n.jpg?stp=dst-jpg_s720x720_tt6\u0026_nc_cat=109\u0026ccb=1-7\u0026_nc_sid=127cfc\u0026_nc_ohc=D8Z4Haf62WkQ7kNvwEXtemZ\u0026_nc_oc=AdlWanWu-e-UjEqaGAcTySz7Qewjy9dmHaSlSyf388OnTiNvJEScf_CzrVz8We1Y-Zc\u0026_nc_zt=23\u0026_nc_ht=scontent-fra5-2.xx\u0026edm=AJdBtusEAAAA\u0026_nc_gid=_TuzWreOdTQAGpM8iVY-4g\u0026oh=00_AfP0VEvSFennbxt1ocsJogjgSNn2Zzt89kDyMffd_-reQg\u0026oe=684E9FB3",
        "is_popular": false,
        "is_published": true,
        "is_hidden": false,
        "is_expired": false,
        "message": "📌 Estimada familia Azulgrana, este Sábado 01 de Junio realizaremos una #PolladaDeConfraternidad con el objetivo de cubrir el desembolso pendiente hacia nuestros deportistas; esperamos su cordial colaboración y apoyemos juntos a nuestro querido club 🗻⚽\n\nLos esperamos en:\n📍 I Calle Pizarro 527, Cercado. \n\n #102AñosdeTradiciónyPasiónAzulgrana  #FBCPiérola #Arequipa",
        "permalink_url": "https://www.facebook.com/337153289263768/posts/445128455132917",
        "from": {
            "name": "FBC Piérola",
            "id": "112828461693258"
        }
    },
    {
        "id": "112828461693258_442804768698619",
        "created_time": "2024-05-27T23:47:41+0000",
        "full_picture": "https://scontent-fra3-1.xx.fbcdn.net/v/t15.5256-10/442087508_842677944432943_2193436883962915785_n.jpg?_nc_cat=101\u0026ccb=1-7\u0026_nc_sid=032300\u0026_nc_ohc=ixlOS-zUHT4Q7kNvwGXhcVN\u0026_nc_oc=Adk0aj0IIoAiuxH4-0rmNwf-vc77QnxaLnrJA7im5d8jRB_AnryFLntfgaoRR03anXs\u0026_nc_zt=23\u0026_nc_ht=scontent-fra3-1.xx\u0026edm=AJdBtusEAAAA\u0026_nc_gid=_TuzWreOdTQAGpM8iVY-4g\u0026oh=00_AfN0hpkFZc_NCp3g27QFO580eBLHie9xBYqFbQlQVJaJSQ\u0026oe=684EC904",
        "is_popular": false,
        "is_published": true,
        "is_hidden": false,
        "is_expired": false,
        "message": "",
        "permalink_url": "https://www.facebook.com/337153289263768/posts/442804768698619",
        "from": {
            "name": "FBC Piérola",
            "id": "112828461693258"
        }
    },
    {
        "id": "112828461693258_442475675398195",
        "created_time": "2024-05-27T12:00:37+0000",
        "full_picture": "https://scontent-fra5-2.xx.fbcdn.net/v/t39.30808-6/480854025_648076484838112_4077545811527905898_n.jpg?stp=dst-jpg_s720x720_tt6\u0026_nc_cat=106\u0026ccb=1-7\u0026_nc_sid=127cfc\u0026_nc_ohc=IhKBzsl5aJ8Q7kNvwEj2EId\u0026_nc_oc=AdnULIyDYxgsjjZIMm7pvBUG8SXuNFBbi6IuUuLkIyqFi2W-KH2tS8L1WDnGhI6bMRY\u0026_nc_zt=23\u0026_nc_ht=scontent-fra5-2.xx\u0026edm=AJdBtusEAAAA\u0026_nc_gid=_TuzWreOdTQAGpM8iVY-4g\u0026oh=00_AfOIBC-64ar9mBVTV3GUgIY9_E1mo9aGgRjKUY7SLIY6cg\u0026oe=684EA685",
        "is_popular": false,
        "is_published": true,
        "is_hidden": false,
        "is_expired": false,
        "message": "Felicitamos encarecidamente al Club Sportivo Huracán por su obtención del campeonato 2024 de la #LigadelCercadoArequipa 🏆 Abrazos fraternos de gol a los jugadores, comando técnico, directivos e hinchas 🗻⚽️ \n\n#FBCPiérola #ClubSportivoHuracán #Arequipa",
        "permalink_url": "https://www.facebook.com/337153289263768/posts/442475675398195",
        "from": {
            "name": "FBC Piérola",
            "id": "112828461693258"
        }
    },
    {
        "id": "112828461693258_442475545398208",
        "created_time": "2024-05-27T12:00:28+0000",
        "full_picture": "https://scontent-fra5-1.xx.fbcdn.net/v/t39.30808-6/481311615_648076494838111_7865592605120449586_n.jpg?stp=dst-jpg_s720x720_tt6\u0026_nc_cat=110\u0026ccb=1-7\u0026_nc_sid=127cfc\u0026_nc_ohc=09bL-NFa61IQ7kNvwHxyvaR\u0026_nc_oc=AdkF_aNvNMcuD8yTXUO4hFPJ2LLnsdq60WUkKhvA0a_Sr16zoqWYSf9pMa6a1x-grmo\u0026_nc_zt=23\u0026_nc_ht=scontent-fra5-1.xx\u0026edm=AJdBtusEAAAA\u0026_nc_gid=_TuzWreOdTQAGpM8iVY-4g\u0026oh=00_AfOPj1H-wScsb5kuUNRUvJ4y7_kOm5iI9mkCkzEbB6yZfQ\u0026oe=684EC080",
        "is_popular": false,
        "is_published": true,
        "is_hidden": false,
        "is_expired": false,
        "message": "Felicitamos encarecidamente al Atletico Universidad Arequipa por su obtención del subcampeonato 2024 de la #LigadelCercadoArequipa 🥈 Abrazos fraternos de gol a los jugadores, comando técnico, directivos e hinchas 🗻⚽️ \n\n#FBCPiérola #AtléticoUniversidadArequipa #Arequipa",
        "permalink_url": "https://www.facebook.com/337153289263768/posts/442475545398208",
        "from": {
            "name": "FBC Piérola",
            "id": "112828461693258"
        }
    },
    {
        "id": "112828461693258_431940566451706",
        "created_time": "2024-05-12T11:00:35+0000",
        "full_picture": "https://scontent-fra3-1.xx.fbcdn.net/v/t39.30808-6/480731820_648053498173744_3142053773059861208_n.jpg?stp=dst-jpg_s720x720_tt6\u0026_nc_cat=108\u0026ccb=1-7\u0026_nc_sid=127cfc\u0026_nc_ohc=fKlaq1zsXksQ7kNvwH9X1Cp\u0026_nc_oc=AdmSTU8S1oWet8b8zVaBzHkYJmg241HUwjtL1iyA-ZXPVY-2uvK8NRCfPqA_95Zlv8E\u0026_nc_zt=23\u0026_nc_ht=scontent-fra3-1.xx\u0026edm=AJdBtusEAAAA\u0026_nc_gid=_TuzWreOdTQAGpM8iVY-4g\u0026oh=00_AfMgh5D1IbBQnxpoER4_BomfBMR-BGz8Gu4J9IGfqxmEAw\u0026oe=684EA713",
        "is_popular": false,
        "is_published": true,
        "is_hidden": false,
        "is_expired": false,
        "message": "En el campo y fuera de él, las madres son nuestro mejor ejemplo de sacrificio, entrega y amor incondicional. En este día especial, queremos enviar un cálido saludo a todas las madres que forman parte de nuestra familia Pierolista. ¡Gracias por ser nuestro motor y nuestra mayor inspiración! ¡Feliz Día de la Madre! 💖⚽\n\n#DíaDeLaMadre #VivaElPiérolaySusMujeres #FBCPiérola #Efemérides",
        "permalink_url": "https://www.facebook.com/337153289263768/posts/431940566451706",
        "from": {
            "name": "FBC Piérola",
            "id": "112828461693258"
        }
    }
]